splitgraph/.git-blame-ignore-revs
splitgraph/BUILD
splitgraph/__init__.py
splitgraph/__version__.py
splitgraph/cloud/BUILD
splitgraph/cloud/__init__.py
splitgraph/cloud/models.py
splitgraph/cloud/project/BUILD
splitgraph/cloud/project/__init__.py
splitgraph/cloud/project/dbt.py
splitgraph/cloud/project/generation.py
splitgraph/cloud/project/github_actions.py
splitgraph/cloud/project/models.py
splitgraph/cloud/project/templates.py
splitgraph/cloud/project/utils.py
splitgraph/cloud/queries.py
splitgraph/commandline/BUILD
splitgraph/commandline/__init__.py
splitgraph/commandline/cloud.py
splitgraph/commandline/common.py
splitgraph/commandline/engine.py
splitgraph/commandline/example.py
splitgraph/commandline/image_creation.py
splitgraph/commandline/image_info.py
splitgraph/commandline/ingestion.py
splitgraph/commandline/misc.py
splitgraph/commandline/mount.py
splitgraph/commandline/push_pull.py
splitgraph/commandline/splitfile.py
splitgraph/config/BUILD
splitgraph/config/__init__.py
splitgraph/config/argument_config.py
splitgraph/config/config.py
splitgraph/config/config_file_config.py
splitgraph/config/default_config.py
splitgraph/config/environment_config.py
splitgraph/config/export.py
splitgraph/config/keys.py
splitgraph/config/management.py
splitgraph/config/system_config.py
splitgraph/core/BUILD
splitgraph/core/__init__.py
splitgraph/core/_drawing.py
splitgraph/core/common.py
splitgraph/core/engine.py
splitgraph/core/fdw_checkout.py
splitgraph/core/fragment_manager.py
splitgraph/core/image.py
splitgraph/core/image_manager.py
splitgraph/core/image_mounting.py
splitgraph/core/indexing/BUILD
splitgraph/core/indexing/__init__.py
splitgraph/core/indexing/bloom.py
splitgraph/core/indexing/range.py
splitgraph/core/metadata_manager.py
splitgraph/core/migration.py
splitgraph/core/object_manager.py
splitgraph/core/output.py
splitgraph/core/overlay.py
splitgraph/core/registry.py
splitgraph/core/repository.py
splitgraph/core/server.py
splitgraph/core/sql/BUILD
splitgraph-0.3.12.dist-info/entry_points.txt
splitgraph-0.3.12.dist-info/LICENSE.md
splitgraph-0.3.12.dist-info/WHEEL
splitgraph-0.3.12.dist-info/METADATA
splitgraph-0.3.12.dist-info/RECORD
