Metadata-Version: 2.1
Name: splitgraph
Version: 0.3.12
Summary: Command line library and Python client for Splitgraph, a version control system for data
Home-page: https://www.splitgraph.com
License: Apache 2.0 modified with Commons Clause
Author: Splitgraph Limited
Requires-Python: >=3.7,<4.0
Classifier: License :: Other/Proprietary License
Classifier: Programming Language :: Python :: 3
Classifier: Programming Language :: Python :: 3.7
Classifier: Programming Language :: Python :: 3.8
Classifier: Programming Language :: Python :: 3.9
Provides-Extra: pandas
Requires-Dist: asciitree (>=0.3.3)
Requires-Dist: cffi (<1.15)
Requires-Dist: chardet (>=4.0.0,<5.0.0)
Requires-Dist: click (>=7,<8)
Requires-Dist: click_log (>=0.3.2)
Requires-Dist: cryptography (>=3.4.0)
Requires-Dist: docker (>=5.0.2)
Requires-Dist: jsonschema (>=3.1.0)
Requires-Dist: minio (>=4)
Requires-Dist: packaging (>=20.1)
Requires-Dist: pandas[ingestion] (==1.1.5); extra == "pandas"
Requires-Dist: parsimonious (>=0.8,<0.9)
Requires-Dist: pglast (==3.4); sys_platform != "win32"
Requires-Dist: psycopg2-binary (>=2,<3)
Requires-Dist: pydantic (>=1.8.1)
Requires-Dist: requests (>=2.22)
Requires-Dist: ruamel.yaml (>=0.17.17,<0.18.0)
Requires-Dist: sodapy (>=2.1)
Requires-Dist: splitgraph-pipelinewise-target-postgres (>=2.1.0)
Requires-Dist: sqlalchemy[ingestion] (>=1.3,<1.4.23); extra == "pandas"
Requires-Dist: tabulate (>=0.8.7)
Requires-Dist: tqdm (>=4.46.0)
Project-URL: Repository, https://github.com/splitgraph/sgr
